hike/__init__.py
hike/__main__.py
hike/commands/__init__.py
hike/commands/main.py
hike/commands/navigation.py
hike/data/__init__.py
hike/data/bookmarks.py
hike/data/command_history.py
hike/data/config.py
hike/data/history.py
hike/data/location_types.py
hike/data/locations.py
hike/editor/__init__.py
hike/editor/commands.py
hike/editor/screen.py
hike/hike.py
hike/icons.py
hike/messages/__init__.py
hike/messages/clipboard.py
hike/messages/command_line.py
hike/messages/history.py
hike/messages/local_view.py
hike/messages/opening.py
hike/providers/__init__.py
hike/providers/bookmarks.py
hike/providers/history.py
hike/providers/main.py
hike/py.typed
hike/screens/__init__.py
hike/screens/main.py
hike/support/__init__.py
hike/support/mouse.py
hike/support/view_in_browser.py
hike/types.py
hike/widgets/__init__.py
hike/widgets/command_line/__init__.py
hike/widgets/command_line/base_command.py
hike/widgets/command_line/change_directory.py
hike/widgets/command_line/general.py
hike/widgets/command_line/obsidian.py
hike/widgets/command_line/open_directory.py
hike/widgets/command_line/open_file.py
hike/widgets/command_line/open_from_forge.py
hike/widgets/command_line/open_url.py
hike/widgets/command_line/widget.py
hike/widgets/navigation/__init__.py
hike/widgets/navigation/bookmarks_view.py
hike/widgets/navigation/history_view.py
hike/widgets/navigation/local_view.py
hike/widgets/navigation/widget.py
hike/widgets/viewer.py
hike-1.2.1.dist-info/licenses/LICENSE
hike-1.2.1.dist-info/WHEEL
hike-1.2.1.dist-info/entry_points.txt
hike-1.2.1.dist-info/METADATA
hike-1.2.1.dist-info/RECORD
