Metadata-Version: 2.4
Name: hike
Version: 1.2.1
Summary: A Markdown browser for the terminal
Keywords: terminal,tui,chui,documentation,markdown,markdown-viewer,file-viewer,file-browser
Author: Dave Pearson
Author-email: Dave Pearson <davep@davep.org>
License-Expression: GPL-3.0-or-later
License-File: LICENSE
Classifier: Development Status :: 5 - Production/Stable
Classifier: Environment :: Console
Classifier: Intended Audience :: Developers
Classifier: Intended Audience :: End Users/Desktop
Classifier: Intended Audience :: Information Technology
Classifier: Intended Audience :: Other Audience
Classifier: Operating System :: MacOS
Classifier: Operating System :: Microsoft :: Windows :: Windows 10
Classifier: Operating System :: Microsoft :: Windows :: Windows 11
Classifier: Operating System :: POSIX :: Linux
Classifier: Programming Language :: Python :: 3 :: Only
Classifier: Programming Language :: Python :: 3
Classifier: Programming Language :: Python :: 3.10
Classifier: Programming Language :: Python :: 3.11
Classifier: Programming Language :: Python :: 3.12
Classifier: Programming Language :: Python :: 3.13
Classifier: Programming Language :: Python :: 3.14
Classifier: Topic :: Software Development :: Documentation
Classifier: Topic :: Terminals
Classifier: Topic :: Text Processing :: Markup :: Markdown
Classifier: Topic :: Utilities
Classifier: Typing :: Typed
Requires-Dist: textual>=5.3.0
Requires-Dist: textual-enhanced>=0.13.0
Requires-Dist: textual-fspicker>=0.4.1
Requires-Dist: xdg-base-dirs>=6.0.2
Requires-Dist: httpx>=0.28.1
Requires-Dist: typing-extensions>=4.12.2
Requires-Dist: pyperclip>=1.9.0
Requires-Python: >=3.10
Project-URL: Discussions, https://github.com/davep/hike/discussions
Project-URL: Documentation, https://hike.davep.dev/
Project-URL: Homepage, https://hike.davep.dev/
Project-URL: Issues, https://github.com/davep/hike/issues
Project-URL: Repository, https://github.com/davep/hike
Project-URL: Source, https://github.com/davep/hike
